grantaxis/__init__.py
grantaxis/analyzer.py
grantaxis/baseline.py
grantaxis/cli.py
grantaxis/config.py
grantaxis/conn.py
grantaxis/diff.py
grantaxis/snapshot.py
grantaxis/templates/report.html
grantaxis_cli-0.1.4.dist-info/METADATA
grantaxis_cli-0.1.4.dist-info/WHEEL
grantaxis_cli-0.1.4.dist-info/entry_points.txt
grantaxis_cli-0.1.4.dist-info/RECORD
