Metadata-Version: 2.1
Name: grantaxis-cli
Version: 0.1.4
Summary: Snowflake access drift scanner
Author: GrantAxis
Author-email: support@grantaxis.io
Requires-Python: >=3.9,<4.0
Classifier: Programming Language :: Python :: 3
Classifier: Programming Language :: Python :: 3.9
Classifier: Programming Language :: Python :: 3.10
Classifier: Programming Language :: Python :: 3.11
Requires-Dist: pyyaml (>=6.0,<7.0)
Requires-Dist: snowflake-connector-python (>=3.9,<4.0)
Requires-Dist: typer (>=0.12,<0.13)
